arkadmin/__init__.py
arkadmin/admin.py
arkadmin/bundle.py
arkadmin/widget.py
arksurvival-0.0.1.dist-info/LICENSE
arksurvival-0.0.1.dist-info/METADATA
arksurvival-0.0.1.dist-info/WHEEL
arksurvival-0.0.1.dist-info/top_level.txt
arksurvival-0.0.1.dist-info/RECORD
